{
    "type": "FeatureCollection", 
    "features": [
        {
            "geometry": {
                "type": "MultiPolygon", 
                "coordinates": [
                    [
                        [
                            [
                                -122.2186406, 
                                37.9949125
                            ], 
                            [
                                -122.2174072, 
                                37.9945608
                            ], 
                            [
                                -122.2200507, 
                                37.9944142
                            ], 
                            [
                                -122.2186406, 
                                37.9949125
                            ]
                        ]
                    ], 
                    [
                        [
                            [
                                -122.2181149, 
                                37.9957173
                            ], 
                            [
                                -122.2182862, 
                                37.9961627
                            ], 
                            [
                                -122.2174072, 
                                37.9961627
                            ], 
                            [
                                -122.2181149, 
                                37.9957173
                            ]
                        ]
                    ], 
                    [
                        [
                            [
                                -122.2181149, 
                                37.9957173
                            ], 
                            [
                                -122.2186406, 
                                37.9949125
                            ], 
                            [
                                -122.2192317, 
                                37.9956202
                            ], 
                            [
                                -122.2181149, 
                                37.9957173
                            ]
                        ]
                    ], 
                    [
                        [
                            [
                                -122.2195854, 
                                37.9948005
                            ], 
                            [
                                -122.2186406, 
                                37.9949125
                            ], 
                            [
                                -122.2200507, 
                                37.9944142
                            ], 
                            [
                                -122.2195854, 
                                37.9948005
                            ]
                        ]
                    ], 
                    [
                        [
                            [
                                -122.2192317, 
                                37.9956202
                            ], 
                            [
                                -122.2186406, 
                                37.9949125
                            ], 
                            [
                                -122.2195854, 
                                37.9948005
                            ], 
                            [
                                -122.2192317, 
                                37.9956202
                            ]
                        ]
                    ], 
                    [
                        [
                            [
                                -122.2200507, 
                                37.9944142
                            ], 
                            [
                                -122.2201538, 
                                37.9944142
                            ], 
                            [
                                -122.2195854, 
                                37.9948005
                            ], 
                            [
                                -122.2200507, 
                                37.9944142
                            ]
                        ]
                    ], 
                    [
                        [
                            [
                                -122.2185807, 
                                37.9961627
                            ], 
                            [
                                -122.2192317, 
                                37.9956202
                            ], 
                            [
                                -122.2201538, 
                                37.9961627
                            ], 
                            [
                                -122.2185807, 
                                37.9961627
                            ]
                        ]
                    ], 
                    [
                        [
                            [
                                -122.2185807, 
                                37.9961627
                            ], 
                            [
                                -122.2182862, 
                                37.9961627
                            ], 
                            [
                                -122.2181149, 
                                37.9957173
                            ], 
                            [
                                -122.2185807, 
                                37.9961627
                            ]
                        ]
                    ], 
                    [
                        [
                            [
                                -122.2181149, 
                                37.9957173
                            ], 
                            [
                                -122.2192317, 
                                37.9956202
                            ], 
                            [
                                -122.2185807, 
                                37.9961627
                            ], 
                            [
                                -122.2181149, 
                                37.9957173
                            ]
                        ]
                    ], 
                    [
                        [
                            [
                                -122.2181149, 
                                37.9957173
                            ], 
                            [
                                -122.2174072, 
                                37.9961627
                            ], 
                            [
                                -122.2174072, 
                                37.995064
                            ], 
                            [
                                -122.2181149, 
                                37.9957173
                            ]
                        ]
                    ], 
                    [
                        [
                            [
                                -122.2174072, 
                                37.995064
                            ], 
                            [
                                -122.2174072, 
                                37.9945608
                            ], 
                            [
                                -122.2186406, 
                                37.9949125
                            ], 
                            [
                                -122.2174072, 
                                37.995064
                            ]
                        ]
                    ], 
                    [
                        [
                            [
                                -122.2174072, 
                                37.995064
                            ], 
                            [
                                -122.2186406, 
                                37.9949125
                            ], 
                            [
                                -122.2181149, 
                                37.9957173
                            ], 
                            [
                                -122.2174072, 
                                37.995064
                            ]
                        ]
                    ], 
                    [
                        [
                            [
                                -122.2201538, 
                                37.9961627
                            ], 
                            [
                                -122.2192317, 
                                37.9956202
                            ], 
                            [
                                -122.2201538, 
                                37.9959578
                            ], 
                            [
                                -122.2201538, 
                                37.9961627
                            ]
                        ]
                    ], 
                    [
                        [
                            [
                                -122.2201538, 
                                37.9959578
                            ], 
                            [
                                -122.2192317, 
                                37.9956202
                            ], 
                            [
                                -122.2195854, 
                                37.9948005
                            ], 
                            [
                                -122.2201538, 
                                37.9959578
                            ]
                        ]
                    ], 
                    [
                        [
                            [
                                -122.2195854, 
                                37.9948005
                            ], 
                            [
                                -122.2201538, 
                                37.9944142
                            ], 
                            [
                                -122.2201538, 
                                37.9959578
                            ], 
                            [
                                -122.2195854, 
                                37.9948005
                            ]
                        ]
                    ]
                ]
            }, 
            "type": "Feature", 
            "properties": {
                "kind": "terrain"
            }
        }
    ]
}