{
    "type": "FeatureCollection", 
    "features": [
        {
            "geometry": {
                "type": "MultiPolygon", 
                "coordinates": [
                    [
                        [
                            [
                                -122.4055093, 
                                37.9369933
                            ], 
                            [
                                -122.4069214, 
                                37.9359161
                            ], 
                            [
                                -122.4047056, 
                                37.9376993
                            ], 
                            [
                                -122.4055093, 
                                37.9369933
                            ]
                        ]
                    ], 
                    [
                        [
                            [
                                -122.4059945, 
                                37.9364584
                            ], 
                            [
                                -122.4047056, 
                                37.9376993
                            ], 
                            [
                                -122.4061363, 
                                37.9363174
                            ], 
                            [
                                -122.4059945, 
                                37.9364584
                            ]
                        ]
                    ], 
                    [
                        [
                            [
                                -122.4059945, 
                                37.9364584
                            ], 
                            [
                                -122.4061363, 
                                37.9363174
                            ], 
                            [
                                -122.4062831, 
                                37.9362312
                            ], 
                            [
                                -122.4059945, 
                                37.9364584
                            ]
                        ]
                    ], 
                    [
                        [
                            [
                                -122.4069, 
                                37.9359308
                            ], 
                            [
                                -122.4069214, 
                                37.9359161
                            ], 
                            [
                                -122.4055093, 
                                37.9369933
                            ], 
                            [
                                -122.4069, 
                                37.9359308
                            ]
                        ]
                    ], 
                    [
                        [
                            [
                                -122.4055093, 
                                37.9369933
                            ], 
                            [
                                -122.4057142, 
                                37.9367493
                            ], 
                            [
                                -122.4069, 
                                37.9359308
                            ], 
                            [
                                -122.4055093, 
                                37.9369933
                            ]
                        ]
                    ], 
                    [
                        [
                            [
                                -122.4069, 
                                37.9359308
                            ], 
                            [
                                -122.4057142, 
                                37.9367493
                            ], 
                            [
                                -122.4059945, 
                                37.9364584
                            ], 
                            [
                                -122.4069, 
                                37.9359308
                            ]
                        ]
                    ], 
                    [
                        [
                            [
                                -122.4062831, 
                                37.9362312
                            ], 
                            [
                                -122.4069214, 
                                37.9359161
                            ], 
                            [
                                -122.4069, 
                                37.9359308
                            ], 
                            [
                                -122.4062831, 
                                37.9362312
                            ]
                        ]
                    ], 
                    [
                        [
                            [
                                -122.4069, 
                                37.9359308
                            ], 
                            [
                                -122.4059945, 
                                37.9364584
                            ], 
                            [
                                -122.4062831, 
                                37.9362312
                            ], 
                            [
                                -122.4069, 
                                37.9359308
                            ]
                        ]
                    ], 
                    [
                        [
                            [
                                -122.4055093, 
                                37.9369933
                            ], 
                            [
                                -122.4047056, 
                                37.9376993
                            ], 
                            [
                                -122.4052544, 
                                37.9371878
                            ], 
                            [
                                -122.4055093, 
                                37.9369933
                            ]
                        ]
                    ], 
                    [
                        [
                            [
                                -122.4052544, 
                                37.9371878
                            ], 
                            [
                                -122.4057142, 
                                37.9367493
                            ], 
                            [
                                -122.4055093, 
                                37.9369933
                            ], 
                            [
                                -122.4052544, 
                                37.9371878
                            ]
                        ]
                    ], 
                    [
                        [
                            [
                                -122.4052544, 
                                37.9371878
                            ], 
                            [
                                -122.4047056, 
                                37.9376993
                            ], 
                            [
                                -122.4059945, 
                                37.9364584
                            ], 
                            [
                                -122.4052544, 
                                37.9371878
                            ]
                        ]
                    ], 
                    [
                        [
                            [
                                -122.4059945, 
                                37.9364584
                            ], 
                            [
                                -122.4057142, 
                                37.9367493
                            ], 
                            [
                                -122.4052544, 
                                37.9371878
                            ], 
                            [
                                -122.4059945, 
                                37.9364584
                            ]
                        ]
                    ]
                ]
            }, 
            "type": "Feature", 
            "properties": {
                "kind": "terrain"
            }
        }
    ]
}